han_solo/__init__.py
pyHanSolo-0.0.1.dist-info/METADATA
pyHanSolo-0.0.1.dist-info/RECORD
pyHanSolo-0.0.1.dist-info/WHEEL
pyHanSolo-0.0.1.dist-info/top_level.txt
