Metadata-Version: 2.1
Name: pyHanSolo
Version: 0.0.1
Summary: A python3 library to communicate with HanSolo
Home-page: https://github.com/Danielhiversen/pyHanSolo
Author: Daniel Hoyer Iversen
Author-email: mail@dahoiv.net
License: MIT
Platform: UNKNOWN
Classifier: Intended Audience :: Developers
Classifier: Operating System :: OS Independent
Classifier: Programming Language :: Python
Classifier: Programming Language :: Python :: 3
Classifier: Topic :: Home Automation
Classifier: Topic :: Software Development :: Libraries :: Python Modules
Requires-Python: >=3.5.3
Requires-Dist: crcmod
Requires-Dist: aiohttp
